ptychography40/__init__.py
ptychography40/__version__.py
ptychography40/_baked_revision.py
ptychography40/versioning.py
ptychography40/reconstruction/common.py
ptychography40/reconstruction/ssb/__init__.py
ptychography40/reconstruction/ssb/trotters.py
ptychography40/reconstruction/ssb/udf.py
ptychography40/stitching/stitching.py
ptychography40-0.1.0.dist-info/LICENSE
ptychography40-0.1.0.dist-info/METADATA
ptychography40-0.1.0.dist-info/WHEEL
ptychography40-0.1.0.dist-info/top_level.txt
ptychography40-0.1.0.dist-info/RECORD
