Metadata-Version: 2.1
Name: ptychography40
Version: 0.1.0
Summary: Phase reconstruction using ptychography
Home-page: https://ptychography-4-0.github.io/ptychography/
Author: the Ptychography 4.0 team
Author-email: ptychography4@listen.helmholtz-muenchen.de
License: GPL v3
Keywords: Ptychography
Platform: UNKNOWN
Classifier: Development Status :: 4 - Beta
Classifier: Programming Language :: Python :: 3.6
Classifier: Programming Language :: Python :: 3.7
Classifier: Programming Language :: Python :: 3.8
Classifier: License :: OSI Approved :: GNU General Public License v3 (GPLv3)
Classifier: License :: OSI Approved :: MIT License
Classifier: Operating System :: POSIX :: Linux
Classifier: Operating System :: MacOS :: MacOS X
Classifier: Operating System :: Microsoft :: Windows
Classifier: Environment :: Console
Classifier: Intended Audience :: Science/Research
Classifier: Natural Language :: English
Classifier: Topic :: Scientific/Engineering
Classifier: Topic :: Scientific/Engineering :: Physics
Classifier: Topic :: Scientific/Engineering :: Visualization
Requires-Python: >=3.6
Requires-Dist: numpy
Requires-Dist: scipy
Requires-Dist: sparse
Requires-Dist: libertem (>=0.7.0)
Requires-Dist: numba (>=0.46)
